senderstats/__init__.py
senderstats/__main__.py
senderstats/cli.py
senderstats/cli_args.py
senderstats/gui.py
senderstats/common/__init__.py
senderstats/common/address_parser.py
senderstats/common/address_tools.py
senderstats/common/defaults.py
senderstats/common/mid_parser.py
senderstats/common/regex_patterns.py
senderstats/common/subject_normalizer.py
senderstats/common/tld_parser.py
senderstats/common/utils.py
senderstats/common/data/default_psl.pkl
senderstats/common/data/name_automaton.pkl
senderstats/core/__init__.py
senderstats/core/filters/__init__.py
senderstats/core/filters/exclude_domain_filter.py
senderstats/core/filters/exclude_duplicate_mid_filter.py
senderstats/core/filters/exclude_empty_sender_filter.py
senderstats/core/filters/exclude_invalid_size_filter.py
senderstats/core/filters/exclude_ip_filter.py
senderstats/core/filters/exclude_sender_filter.py
senderstats/core/filters/restrict_domain_filter.py
senderstats/core/mappers/__init__.py
senderstats/core/mappers/csv_mapper.py
senderstats/core/processors/__init__.py
senderstats/core/processors/alignment_processor.py
senderstats/core/processors/date_processor.py
senderstats/core/processors/hfrom_processor.py
senderstats/core/processors/mfrom_processor.py
senderstats/core/processors/mid_processor.py
senderstats/core/processors/rpath_processor.py
senderstats/core/transformers/__init__.py
senderstats/core/transformers/date_transform.py
senderstats/core/transformers/hfrom_transform.py
senderstats/core/transformers/mfrom_transform.py
senderstats/core/transformers/mid_transform.py
senderstats/core/transformers/rpath_transform.py
senderstats/core/validators/__init__.py
senderstats/data/__init__.py
senderstats/data/csv_data_source.py
senderstats/data/data_source_type.py
senderstats/data/message_data.py
senderstats/images/senderstats.ico
senderstats/images/senderstats.png
senderstats/interfaces/__init__.py
senderstats/interfaces/criteria.py
senderstats/interfaces/data_source.py
senderstats-2.1.2.dist-info/licenses/LICENSE
senderstats-2.1.2.dist-info/METADATA
senderstats-2.1.2.dist-info/WHEEL
senderstats-2.1.2.dist-info/entry_points.txt
senderstats-2.1.2.dist-info/top_level.txt
senderstats-2.1.2.dist-info/RECORD
