Metadata-Version: 2.4
Name: senderstats
Version: 2.1.2
Summary: Tool to Process Smart Search Results and Identify Top Senders
License: MIT
Project-URL: repository, https://github.com/pfptcommunity/senderstats
Requires-Python: >3.9
License-File: LICENSE
Requires-Dist: xlsxwriter
Requires-Dist: regex
Requires-Dist: google-re2
Requires-Dist: pyahocorasick
Requires-Dist: ciso8601
Provides-Extra: gui
Requires-Dist: tkinterdnd2; extra == "gui"
Dynamic: license-file
